mqtfy/__init__.py
mqtfy/config_loader.py
mqtfy/main.py
mqtfy-0.3.1.dist-info/licenses/LICENSE
mqtfy-0.3.1.dist-info/METADATA
mqtfy-0.3.1.dist-info/WHEEL
mqtfy-0.3.1.dist-info/entry_points.txt
mqtfy-0.3.1.dist-info/top_level.txt
mqtfy-0.3.1.dist-info/RECORD
